Metadata-Version: 2.1
Name: KetoGator
Version: 1.0.16
Summary: Data entry and retrieval
Home-page: https://github.com/KylerKatz/KetoGator
Author: KGTeam
Author-email: christensend@ufl.edu
License: UNKNOWN
Platform: UNKNOWN
Requires-Python: >=3.8, <4
Requires-Dist: PyQt5
Requires-Dist: pandas
Requires-Dist: xlrd
Requires-Dist: xlwt
Requires-Dist: mysql-connector-python
Requires-Dist: openpyxl
Requires-Dist: matplotlib
